<mockup version="4.5" minAllowVersion="4.5" ID="149027B6-BEF9-49AC-BFB6-3DBDEBD6330E" platform="MtMobile" defaultW="375" defaultH="667" screenOrientation="MoPortrait" mobileScreenScale="1.77777779102325" measureW="375" measureH="667" clipArea="(0,0,0,0)">
  <controls controlCount="24">
    <control controlID="2263FD80-6440-496A-80CB-F786BA3E259B" controlTypeID="Top ActionBar" isShow="True" caption="%E9%A1%B6%E9%83%A8%E6%93%8D%E4%BD%9C%E6%A0%8F" x="0" y="0" w="375" h="48" measuredW="342" measuredH="48" zOrder="0" locked="False" sizeLocked="False">
      <controlProperties>
        <basic color="4292730333" borderVisible="True" borderColor="4284900966" isAutoSize="False" status="MsEnabled" opacity="1" isCommentCom="False" canMove="True" alias="" rotation="0"/>
        <states/>
        <verticalScrollbarShow>False</verticalScrollbarShow>
        <verticalScrollbarProgress>0</verticalScrollbarProgress>
        <horizontalScrollbarShow>False</horizontalScrollbarShow>
        <horizontalScrollbarProgress>0</horizontalScrollbarProgress>
        <links eventType="AtClick" animate="AmNone" animateAutoDelay="0" animateDuration="500">
          <link targetPageID="" linkType="ltPageLink" isApplyIncludePage="False" title="%E8%BF%94%E5%9B%9E">
            <area shape="0" alt="" ID="{6B185559-50C2-4337-95CD-FFD7CF74F169}" coords="(2,4,42,44)"/>
          </link>
          <link targetPageID="" linkType="ltPageLink" isApplyIncludePage="False" title="%E8%8F%9C%E5%8D%95">
            <area shape="0" alt="" ID="{1D387646-77C2-4CC7-B68C-51329E4B58C1}" coords="(328,4,368,44)"/>
          </link>
        </links>
        <interactiveData>
          <entry title="%E8%BF%94%E5%9B%9E">
            <area shape="0" alt="" ID="{2A3A2246-91E9-464A-8D24-61D0B5CBAA91}" coords="(2,4,42,44)"/>
            <events title=""/>
          </entry>
          <entry title="%E8%8F%9C%E5%8D%95">
            <area shape="0" alt="" ID="{8F4B8A59-8E50-4C31-989A-46B7AFCCBE14}" coords="(328,4,368,44)"/>
            <events title=""/>
          </entry>
        </interactiveData>
        <textSet textColor="4278190080" textSize="20" lineSpacingMultiple="1" textAlign="HaLeft" textVAlign="VaTop" textWordWrap="True" lineSpacing="26" textStyles="[]" useDefaultTextSize="False">
          <font family="%E5%BE%AE%E8%BD%AF%E9%9B%85%E9%BB%91" displayName="%E5%BE%AE%E8%BD%AF%E9%9B%85%E9%BB%91" postScript="" weightStyle="Regular" weight="400" isBold="False" isItalic="False"/>
          <text>%E5%B8%82%E9%95%BF%E4%BF%A1%E7%AE%B1</text>
        </textSet>
        <selectedIndex>0</selectedIndex>
        <selectedColor>4282501083</selectedColor>
        <textPadding>0</textPadding>
        <showMenu>True</showMenu>
        <showBack>True</showBack>
        <iconColor>4278190080</iconColor>
      </controlProperties>
    </control>
    <control controlID="5AF5955E-9D8A-4E69-8A32-B9D03BF370D6" controlTypeID="__group__" isShow="True" caption="%E7%BB%84" x="40" y="419" w="235" h="39" measuredW="0" measuredH="0" zOrder="1" locked="False" sizeLocked="False">
      <controlProperties>
        <basic color="4294967295" borderVisible="True" borderColor="4284900966" isAutoSize="False" status="MsEnabled" opacity="1" isCommentCom="False" canMove="True" alias="" rotation="0"/>
        <states/>
        <verticalScrollbarShow>False</verticalScrollbarShow>
        <verticalScrollbarProgress>0</verticalScrollbarProgress>
        <horizontalScrollbarShow>False</horizontalScrollbarShow>
        <horizontalScrollbarProgress>0</horizontalScrollbarProgress>
        <links eventType="AtClick" animate="AmNone" animateAutoDelay="0" animateDuration="500">
          <link targetPageID="" linkType="ltPageLink" isApplyIncludePage="False" title="%E9%93%BE%E6%8E%A5">
            <area shape="0" alt="" ID="{F368E4D3-D873-4C53-BBB8-54E6F4F5D3A9}" coords="(0,0,235,39)"/>
          </link>
        </links>
        <interactiveData>
          <entry title="">
            <area shape="0" alt="" ID="{2D5FD045-B850-4E29-887A-1E8BA039684F}" coords="(0,0,235,39)"/>
            <events title=""/>
          </entry>
        </interactiveData>
        <groupChildrenDescriptors>
          <control controlID="786C1522-C6DA-4341-BF9B-85E097FAF46B" controlTypeID="TextInput" isShow="True" caption="%E8%BE%93%E5%85%A5%E6%A1%86" x="97" y="0" w="138" h="39" measuredW="138" measuredH="36" zOrder="0" locked="False" sizeLocked="False">
            <controlProperties>
              <basic color="4294967295" borderVisible="True" borderColor="4284900966" isAutoSize="False" status="MsEnabled" opacity="1" isCommentCom="False" canMove="True" alias="" rotation="0"/>
              <states/>
              <verticalScrollbarShow>False</verticalScrollbarShow>
              <verticalScrollbarProgress>0</verticalScrollbarProgress>
              <horizontalScrollbarShow>False</horizontalScrollbarShow>
              <horizontalScrollbarProgress>0</horizontalScrollbarProgress>
              <links eventType="AtClick" animate="AmNone" animateAutoDelay="0" animateDuration="500">
                <link targetPageID="" linkType="ltPageLink" isApplyIncludePage="False" title="%E9%93%BE%E6%8E%A5">
                  <area shape="0" alt="" ID="{87D43BA6-ECE6-413C-A42D-57BD89FA2E33}" coords="(0,0,138,39)"/>
                </link>
              </links>
              <interactiveData>
                <entry title="">
                  <area shape="0" alt="" ID="{9C4D8198-4453-45CF-8DAB-7AFC7004E938}" coords="(0,0,138,39)"/>
                  <events title=""/>
                </entry>
              </interactiveData>
              <textSet textColor="4278190080" textSize="14" lineSpacingMultiple="1" textAlign="HaLeft" textVAlign="VaMiddle" textWordWrap="True" lineSpacing="18" textStyles="[]" useDefaultTextSize="True">
                <font family="%E5%BE%AE%E8%BD%AF%E9%9B%85%E9%BB%91" displayName="%E5%BE%AE%E8%BD%AF%E9%9B%85%E9%BB%91" postScript="" weightStyle="Regular" weight="400" isBold="False" isItalic="False"/>
              </textSet>
              <selectedIndex>-1</selectedIndex>
              <selectedColor>4282501083</selectedColor>
              <textPadding>0</textPadding>
              <canInput>True</canInput>
            </controlProperties>
          </control>
          <control controlID="E36E9AEE-651D-4821-A342-B8C4A6368CA6" controlTypeID="Label" isShow="True" caption="%E5%8D%95%E8%A1%8C%E6%96%87%E5%AD%97" x="0" y="8" w="54" h="24" measuredW="0" measuredH="0" zOrder="1" locked="False" sizeLocked="False">
            <controlProperties>
              <basic color="0" borderVisible="True" borderColor="4284900966" isAutoSize="True" status="MsEnabled" opacity="1" isCommentCom="False" canMove="True" alias="" rotation="0"/>
              <states/>
              <verticalScrollbarShow>False</verticalScrollbarShow>
              <verticalScrollbarProgress>0</verticalScrollbarProgress>
              <horizontalScrollbarShow>False</horizontalScrollbarShow>
              <horizontalScrollbarProgress>0</horizontalScrollbarProgress>
              <links eventType="AtClick" animate="AmNone" animateAutoDelay="0" animateDuration="500">
                <link targetPageID="" linkType="ltPageLink" isApplyIncludePage="False" title="%E9%93%BE%E6%8E%A5">
                  <area shape="0" alt="" ID="{B5DD3AEC-4156-4457-B986-F4619B580549}" coords="(0,0,54,24)"/>
                </link>
              </links>
              <interactiveData>
                <entry title="">
                  <area shape="0" alt="" ID="{279A08D6-AE05-49EF-BB83-85397CDB9418}" coords="(0,0,54,24)"/>
                  <events title=""/>
                </entry>
              </interactiveData>
              <textSet textColor="4278190080" textSize="18" lineSpacingMultiple="1" textAlign="HaLeft" textVAlign="VaTop" textWordWrap="True" lineSpacing="24" textStyles="[]" useDefaultTextSize="False">
                <font family="%E5%BE%AE%E8%BD%AF%E9%9B%85%E9%BB%91" displayName="%E5%BE%AE%E8%BD%AF%E9%9B%85%E9%BB%91" postScript="" weightStyle="Regular" weight="400" isBold="False" isItalic="False"/>
                <text>%E6%89%8B%E6%9C%BA%E5%8F%B7</text>
              </textSet>
              <selectedIndex>-1</selectedIndex>
              <selectedColor>4282501083</selectedColor>
              <textPadding>0</textPadding>
            </controlProperties>
          </control>
        </groupChildrenDescriptors>
      </controlProperties>
    </control>
    <control controlID="973E0F3B-59FB-4A38-9687-E6625A5B0FC7" controlTypeID="TextInput" isShow="True" caption="%E8%BE%93%E5%85%A5%E6%A1%86" x="137" y="147" w="195" h="97" measuredW="138" measuredH="36" zOrder="2" locked="False" sizeLocked="False">
      <controlProperties>
        <basic color="4294967295" borderVisible="True" borderColor="4284900966" isAutoSize="False" status="MsEnabled" opacity="1" isCommentCom="False" canMove="True" alias="" rotation="0"/>
        <states/>
        <verticalScrollbarShow>False</verticalScrollbarShow>
        <verticalScrollbarProgress>0</verticalScrollbarProgress>
        <horizontalScrollbarShow>False</horizontalScrollbarShow>
        <horizontalScrollbarProgress>0</horizontalScrollbarProgress>
        <links eventType="AtClick" animate="AmNone" animateAutoDelay="0" animateDuration="500">
          <link targetPageID="" linkType="ltPageLink" isApplyIncludePage="False" title="%E9%93%BE%E6%8E%A5">
            <area shape="0" alt="" ID="{87D43BA6-ECE6-413C-A42D-57BD89FA2E33}" coords="(0,0,195,97)"/>
          </link>
        </links>
        <interactiveData>
          <entry title="">
            <area shape="0" alt="" ID="{9C4D8198-4453-45CF-8DAB-7AFC7004E938}" coords="(0,0,195,97)"/>
            <events title=""/>
          </entry>
        </interactiveData>
        <textSet textColor="4278190080" textSize="14" lineSpacingMultiple="1" textAlign="HaLeft" textVAlign="VaMiddle" textWordWrap="True" lineSpacing="18" textStyles="[]" useDefaultTextSize="True">
          <font family="%E5%BE%AE%E8%BD%AF%E9%9B%85%E9%BB%91" displayName="%E5%BE%AE%E8%BD%AF%E9%9B%85%E9%BB%91" postScript="" weightStyle="Regular" weight="400" isBold="False" isItalic="False"/>
          <text>%E8%BE%93%E5%85%A5%E6%A1%86</text>
        </textSet>
        <selectedIndex>-1</selectedIndex>
        <selectedColor>4282501083</selectedColor>
        <textPadding>0</textPadding>
        <canInput>True</canInput>
      </controlProperties>
    </control>
    <control controlID="814CC467-494D-4030-8EBD-CFA47F6C7F0C" controlTypeID="Label" isShow="True" caption="%E5%8D%95%E8%A1%8C%E6%96%87%E5%AD%97" x="40" y="144" w="36" h="24" measuredW="0" measuredH="0" zOrder="3" locked="False" sizeLocked="False">
      <controlProperties>
        <basic color="0" borderVisible="True" borderColor="4284900966" isAutoSize="True" status="MsEnabled" opacity="1" isCommentCom="False" canMove="True" alias="" rotation="0"/>
        <states/>
        <verticalScrollbarShow>False</verticalScrollbarShow>
        <verticalScrollbarProgress>0</verticalScrollbarProgress>
        <horizontalScrollbarShow>False</horizontalScrollbarShow>
        <horizontalScrollbarProgress>0</horizontalScrollbarProgress>
        <links eventType="AtClick" animate="AmNone" animateAutoDelay="0" animateDuration="500">
          <link targetPageID="" linkType="ltPageLink" isApplyIncludePage="False" title="%E9%93%BE%E6%8E%A5">
            <area shape="0" alt="" ID="{B5DD3AEC-4156-4457-B986-F4619B580549}" coords="(0,0,36,24)"/>
          </link>
        </links>
        <interactiveData>
          <entry title="">
            <area shape="0" alt="" ID="{279A08D6-AE05-49EF-BB83-85397CDB9418}" coords="(0,0,36,24)"/>
            <events title=""/>
          </entry>
        </interactiveData>
        <textSet textColor="4278190080" textSize="18" lineSpacingMultiple="1" textAlign="HaLeft" textVAlign="VaTop" textWordWrap="True" lineSpacing="24" textStyles="[]" useDefaultTextSize="False">
          <font family="%E5%BE%AE%E8%BD%AF%E9%9B%85%E9%BB%91" displayName="%E5%BE%AE%E8%BD%AF%E9%9B%85%E9%BB%91" postScript="" weightStyle="Regular" weight="400" isBold="False" isItalic="False"/>
          <text>%E5%86%85%E5%AE%B9</text>
        </textSet>
        <selectedIndex>-1</selectedIndex>
        <selectedColor>4282501083</selectedColor>
        <textPadding>0</textPadding>
      </controlProperties>
    </control>
    <control controlID="5CE2EE38-FA65-4699-A628-10BD151CCB85" controlTypeID="TextInput" isShow="True" caption="%E8%BE%93%E5%85%A5%E6%A1%86" x="137" y="368" w="138" h="29" measuredW="138" measuredH="36" zOrder="4" locked="False" sizeLocked="False">
      <controlProperties>
        <basic color="4294967295" borderVisible="True" borderColor="4284900966" isAutoSize="False" status="MsEnabled" opacity="1" isCommentCom="False" canMove="True" alias="" rotation="0"/>
        <states/>
        <verticalScrollbarShow>False</verticalScrollbarShow>
        <verticalScrollbarProgress>0</verticalScrollbarProgress>
        <horizontalScrollbarShow>False</horizontalScrollbarShow>
        <horizontalScrollbarProgress>0</horizontalScrollbarProgress>
        <links eventType="AtClick" animate="AmNone" animateAutoDelay="0" animateDuration="500">
          <link targetPageID="" linkType="ltPageLink" isApplyIncludePage="False" title="%E9%93%BE%E6%8E%A5">
            <area shape="0" alt="" ID="{87D43BA6-ECE6-413C-A42D-57BD89FA2E33}" coords="(0,0,138,29)"/>
          </link>
        </links>
        <interactiveData>
          <entry title="">
            <area shape="0" alt="" ID="{9C4D8198-4453-45CF-8DAB-7AFC7004E938}" coords="(0,0,138,29)"/>
            <events title=""/>
          </entry>
        </interactiveData>
        <textSet textColor="4278190080" textSize="14" lineSpacingMultiple="1" textAlign="HaLeft" textVAlign="VaMiddle" textWordWrap="True" lineSpacing="18" textStyles="[]" useDefaultTextSize="True">
          <font family="%E5%BE%AE%E8%BD%AF%E9%9B%85%E9%BB%91" displayName="%E5%BE%AE%E8%BD%AF%E9%9B%85%E9%BB%91" postScript="" weightStyle="Regular" weight="400" isBold="False" isItalic="False"/>
        </textSet>
        <selectedIndex>-1</selectedIndex>
        <selectedColor>4282501083</selectedColor>
        <textPadding>0</textPadding>
        <canInput>True</canInput>
      </controlProperties>
    </control>
    <control controlID="BEE95B34-0F94-402F-A6F8-A8F90960F5A7" controlTypeID="Label" isShow="True" caption="%E5%8D%95%E8%A1%8C%E6%96%87%E5%AD%97" x="40" y="373" w="34" h="24" measuredW="0" measuredH="0" zOrder="5" locked="False" sizeLocked="False">
      <controlProperties>
        <basic color="0" borderVisible="True" borderColor="4284900966" isAutoSize="True" status="MsEnabled" opacity="1" isCommentCom="False" canMove="True" alias="" rotation="0"/>
        <states/>
        <verticalScrollbarShow>False</verticalScrollbarShow>
        <verticalScrollbarProgress>0</verticalScrollbarProgress>
        <horizontalScrollbarShow>False</horizontalScrollbarShow>
        <horizontalScrollbarProgress>0</horizontalScrollbarProgress>
        <links eventType="AtClick" animate="AmNone" animateAutoDelay="0" animateDuration="500">
          <link targetPageID="" linkType="ltPageLink" isApplyIncludePage="False" title="%E9%93%BE%E6%8E%A5">
            <area shape="0" alt="" ID="{B5DD3AEC-4156-4457-B986-F4619B580549}" coords="(0,0,34,24)"/>
          </link>
        </links>
        <interactiveData>
          <entry title="">
            <area shape="0" alt="" ID="{279A08D6-AE05-49EF-BB83-85397CDB9418}" coords="(0,0,34,24)"/>
            <events title=""/>
          </entry>
        </interactiveData>
        <textSet textColor="4278190080" textSize="18" lineSpacingMultiple="1" textAlign="HaLeft" textVAlign="VaTop" textWordWrap="True" lineSpacing="24" textStyles="[]" useDefaultTextSize="False">
          <font family="%E5%BE%AE%E8%BD%AF%E9%9B%85%E9%BB%91" displayName="%E5%BE%AE%E8%BD%AF%E9%9B%85%E9%BB%91" postScript="" weightStyle="Regular" weight="400" isBold="False" isItalic="False"/>
          <text>%E5%A7%93%E5%90%8D</text>
        </textSet>
        <selectedIndex>-1</selectedIndex>
        <selectedColor>4282501083</selectedColor>
        <textPadding>0</textPadding>
      </controlProperties>
    </control>
    <control controlID="75494279-8FF9-4340-A17F-CD1AC9B329D2" controlTypeID="Label" isShow="True" caption="%E5%8D%95%E8%A1%8C%E6%96%87%E5%AD%97" x="40" y="282" w="72" h="24" measuredW="0" measuredH="0" zOrder="6" locked="False" sizeLocked="False">
      <controlProperties>
        <basic color="0" borderVisible="True" borderColor="4284900966" isAutoSize="True" status="MsEnabled" opacity="1" isCommentCom="False" canMove="True" alias="" rotation="0"/>
        <states/>
        <verticalScrollbarShow>False</verticalScrollbarShow>
        <verticalScrollbarProgress>0</verticalScrollbarProgress>
        <horizontalScrollbarShow>False</horizontalScrollbarShow>
        <horizontalScrollbarProgress>0</horizontalScrollbarProgress>
        <links eventType="AtClick" animate="AmNone" animateAutoDelay="0" animateDuration="500">
          <link targetPageID="" linkType="ltPageLink" isApplyIncludePage="False" title="%E9%93%BE%E6%8E%A5">
            <area shape="0" alt="" ID="{B5DD3AEC-4156-4457-B986-F4619B580549}" coords="(0,0,72,24)"/>
          </link>
        </links>
        <interactiveData>
          <entry title="">
            <area shape="0" alt="" ID="{279A08D6-AE05-49EF-BB83-85397CDB9418}" coords="(0,0,72,24)"/>
            <events title=""/>
          </entry>
        </interactiveData>
        <textSet textColor="4278190080" textSize="18" lineSpacingMultiple="1" textAlign="HaLeft" textVAlign="VaTop" textWordWrap="True" lineSpacing="24" textStyles="[]" useDefaultTextSize="False">
          <font family="%E5%BE%AE%E8%BD%AF%E9%9B%85%E9%BB%91" displayName="%E5%BE%AE%E8%BD%AF%E9%9B%85%E9%BB%91" postScript="" weightStyle="Regular" weight="400" isBold="False" isItalic="False"/>
          <text>%E9%97%AE%E9%A2%98%E5%B1%9E%E5%9C%B0</text>
        </textSet>
        <selectedIndex>-1</selectedIndex>
        <selectedColor>4282501083</selectedColor>
        <textPadding>0</textPadding>
      </controlProperties>
    </control>
    <control controlID="2B67E745-4B93-463A-90CD-41671FA33791" controlTypeID="CompositeComboBox" isShow="True" caption="%E4%B8%8B%E6%8B%89%E5%88%97%E8%A1%A8%E6%A1%86" x="137" y="276" w="200" h="29" measuredW="102" measuredH="36" zOrder="7" locked="False" sizeLocked="False">
      <controlProperties>
        <basic color="4294967295" borderVisible="True" borderColor="4284900966" isAutoSize="False" status="MsEnabled" opacity="1" isCommentCom="False" canMove="True" alias="" rotation="0"/>
        <states/>
        <verticalScrollbarShow>False</verticalScrollbarShow>
        <verticalScrollbarProgress>0</verticalScrollbarProgress>
        <horizontalScrollbarShow>False</horizontalScrollbarShow>
        <horizontalScrollbarProgress>0</horizontalScrollbarProgress>
        <links eventType="AtClick" animate="AmNone" animateAutoDelay="0" animateDuration="500">
          <link targetPageID="" linkType="ltPageLink" isApplyIncludePage="False" title="%E9%93%BE%E6%8E%A5">
            <area shape="0" alt="" ID="{58CF3410-68EE-40A6-BE1B-A973895AECB5}" coords="(0,0,200,29)"/>
          </link>
        </links>
        <interactiveData>
          <entry title="">
            <area shape="0" alt="" ID="{F84EDEA8-0F62-4439-A6B0-03782DE94958}" coords="(0,0,200,29)"/>
            <events title=""/>
          </entry>
        </interactiveData>
        <groupChildrenDescriptors>
          <control controlID="1A8333A4-A705-446A-AF3B-E257E03A5B71" controlTypeID="TextInput" isShow="True" caption="%E8%BE%93%E5%85%A5%E6%A1%86" x="0" y="0" w="177" h="29" measuredW="138" measuredH="36" zOrder="0" locked="True" sizeLocked="False">
            <controlProperties>
              <basic color="4294967295" borderVisible="True" borderColor="4284900966" isAutoSize="False" status="MsEnabled" opacity="1" isCommentCom="False" canMove="False" alias="input" rotation="0"/>
              <states/>
              <verticalScrollbarShow>False</verticalScrollbarShow>
              <verticalScrollbarProgress>0</verticalScrollbarProgress>
              <horizontalScrollbarShow>False</horizontalScrollbarShow>
              <horizontalScrollbarProgress>0</horizontalScrollbarProgress>
              <links eventType="AtClick" animate="AmNone" animateAutoDelay="0" animateDuration="500">
                <link targetPageID="" linkType="ltPageLink" isApplyIncludePage="False" title="%E9%93%BE%E6%8E%A5">
                  <area shape="0" alt="" ID="{3ECF4D14-1926-4CA4-B836-BD4D37D3EF10}" coords="(0,0,177,29)"/>
                </link>
              </links>
              <interactiveData>
                <entry title="">
                  <area shape="0" alt="" ID="{9BF777AF-3FA3-454F-87FB-E083436FFF38}" coords="(0,0,177,29)"/>
                  <events title=""/>
                </entry>
              </interactiveData>
              <textSet textColor="4278190080" textSize="14" lineSpacingMultiple="1" textAlign="HaLeft" textVAlign="VaMiddle" textWordWrap="True" lineSpacing="18" textStyles="[]" useDefaultTextSize="True">
                <font family="%E5%BE%AE%E8%BD%AF%E9%9B%85%E9%BB%91" displayName="%E5%BE%AE%E8%BD%AF%E9%9B%85%E9%BB%91" postScript="" weightStyle="Regular" weight="400" isBold="False" isItalic="False"/>
                <text>%E6%AD%A6%E6%B1%89</text>
              </textSet>
              <selectedIndex>-1</selectedIndex>
              <selectedColor>4282501083</selectedColor>
              <textPadding>0</textPadding>
              <canInput>True</canInput>
            </controlProperties>
          </control>
          <control controlID="5283301C-B99C-4688-897E-6B2B06FAD1B0" controlTypeID="Button" isShow="True" caption="%E6%8C%89%E9%92%AE" x="176" y="0" w="24" h="29" measuredW="78" measuredH="36" zOrder="1" locked="True" sizeLocked="False">
            <controlProperties>
              <basic color="4294967295" borderVisible="True" borderColor="4284900966" isAutoSize="False" status="MsEnabled" opacity="1" isCommentCom="False" canMove="False" alias="button" rotation="0"/>
              <states/>
              <verticalScrollbarShow>False</verticalScrollbarShow>
              <verticalScrollbarProgress>0</verticalScrollbarProgress>
              <horizontalScrollbarShow>False</horizontalScrollbarShow>
              <horizontalScrollbarProgress>0</horizontalScrollbarProgress>
              <links eventType="AtClick" animate="AmNone" animateAutoDelay="0" animateDuration="500">
                <link targetPageID="" linkType="ltPageLink" isApplyIncludePage="False" title="%E9%93%BE%E6%8E%A5">
                  <area shape="0" alt="" ID="{DA2AD9E1-E4CC-4E95-9D3C-34F97F359AFF}" coords="(0,0,24,29)"/>
                </link>
              </links>
              <interactiveData>
                <entry title="">
                  <area shape="0" alt="" ID="{93DEF7E2-6133-4481-8841-7CE9DCA211F7}" coords="(0,0,24,29)"/>
                  <events title=""/>
                </entry>
              </interactiveData>
              <textSet textColor="4278190080" textSize="14" lineSpacingMultiple="1" textAlign="HaCenter" textVAlign="VaMiddle" textWordWrap="True" lineSpacing="18" textStyles="[]" useDefaultTextSize="True">
                <font family="%E5%BE%AE%E8%BD%AF%E9%9B%85%E9%BB%91" displayName="%E5%BE%AE%E8%BD%AF%E9%9B%85%E9%BB%91" postScript="" weightStyle="Regular" weight="400" isBold="False" isItalic="False"/>
              </textSet>
              <selectedIndex>-1</selectedIndex>
              <selectedColor>4282501083</selectedColor>
              <textPadding>0</textPadding>
              <radius>0</radius>
              <radiusIsPercent>False</radiusIsPercent>
              <buttonStatus>BsNormal</buttonStatus>
              <thickness>1</thickness>
              <isAutoTextColor>False</isAutoTextColor>
              <borderColor>4284900966</borderColor>
            </controlProperties>
          </control>
          <control controlID="CE10F1C9-3B05-4033-ABC5-6C9F7AB9B4A8" controlTypeID="List" isShow="False" caption="%E5%88%97%E8%A1%A8" x="0" y="29" w="200" h="156" measuredW="168" measuredH="252" zOrder="2" locked="False" sizeLocked="False">
            <controlProperties>
              <basic color="4294967295" borderVisible="True" borderColor="4284900966" isAutoSize="False" status="MsEnabled" opacity="1" isCommentCom="False" canMove="False" alias="dropDown" rotation="0"/>
              <states/>
              <verticalScrollbarShow>False</verticalScrollbarShow>
              <verticalScrollbarProgress>0</verticalScrollbarProgress>
              <horizontalScrollbarShow>False</horizontalScrollbarShow>
              <horizontalScrollbarProgress>0</horizontalScrollbarProgress>
              <links eventType="AtClick" animate="AmNone" animateAutoDelay="0" animateDuration="500">
                <link targetPageID="" linkType="ltPageLink" isApplyIncludePage="False" title="%E6%AD%A6%E6%B1%89">
                  <area shape="0" alt="" ID="{EFC6596B-81C8-419B-8962-3A008462AF24}" coords="(1,1,199,40)"/>
                </link>
                <link targetPageID="" linkType="ltPageLink" isApplyIncludePage="False" title="%E9%95%BF%E6%B2%99">
                  <area shape="0" alt="" ID="{A295F4C9-D287-4189-A793-68659AA6E6E6}" coords="(1,40,199,79)"/>
                </link>
                <link targetPageID="" linkType="ltPageLink" isApplyIncludePage="False" title="%E5%8D%97%E6%98%8C">
                  <area shape="0" alt="" ID="{DFC49E78-1ED2-4369-BF4F-B16641B13A24}" coords="(1,79,199,118)"/>
                </link>
                <link targetPageID="" linkType="ltPageLink" isApplyIncludePage="False" title="%E5%90%88%E8%82%A5">
                  <area shape="0" alt="" ID="{4DA82B08-2BB0-411C-B70B-B7BD6D2114D9}" coords="(1,118,199,156)"/>
                </link>
              </links>
              <interactiveData>
                <entry title="%E6%AD%A6%E6%B1%89">
                  <area shape="0" alt="" ID="{FC98BBE3-1B67-4283-956A-B386D0ED10C7}" coords="(1,1,199,40)"/>
                  <events title=""/>
                </entry>
                <entry title="%E9%95%BF%E6%B2%99">
                  <area shape="0" alt="" ID="{B7EBC974-6F46-4C0F-BFD5-212E8F744004}" coords="(1,40,199,79)"/>
                  <events title=""/>
                </entry>
                <entry title="%E5%8D%97%E6%98%8C">
                  <area shape="0" alt="" ID="{6C4B7968-26F4-4542-AD4B-2E38AEF68F96}" coords="(1,79,199,118)"/>
                  <events title=""/>
                </entry>
                <entry title="%E5%90%88%E8%82%A5">
                  <area shape="0" alt="" ID="{4AD130E2-7756-4C80-ABE0-267109280E8E}" coords="(1,118,199,156)"/>
                  <events title=""/>
                </entry>
              </interactiveData>
              <textSet textColor="4278190080" textSize="14" lineSpacingMultiple="1" textAlign="HaLeft" textVAlign="VaTop" textWordWrap="True" lineSpacing="18" textStyles="[]" useDefaultTextSize="True">
                <font family="%E5%BE%AE%E8%BD%AF%E9%9B%85%E9%BB%91" displayName="%E5%BE%AE%E8%BD%AF%E9%9B%85%E9%BB%91" postScript="" weightStyle="Regular" weight="400" isBold="False" isItalic="False"/>
                <text>%E6%AD%A6%E6%B1%89%0D%0A%E9%95%BF%E6%B2%99%0D%0A%E5%8D%97%E6%98%8C%0D%0A%E5%90%88%E8%82%A5</text>
              </textSet>
              <selectedIndex>0</selectedIndex>
              <selectedColor>4282501083</selectedColor>
              <textPadding>10</textPadding>
              <itemHeight>29</itemHeight>
              <isInterlace>False</isInterlace>
              <interlaceColor>4294967295</interlaceColor>
              <separatorColor>4284900966</separatorColor>
              <showSeparator>False</showSeparator>
            </controlProperties>
          </control>
        </groupChildrenDescriptors>
        <rowCount>5</rowCount>
        <canInput>False</canInput>
        <baseHeight>29</baseHeight>
        <textSet textColor="4278190080" textSize="14" textStyles="[]">
          <font family="%E5%BE%AE%E8%BD%AF%E9%9B%85%E9%BB%91"/>
        </textSet>
      </controlProperties>
    </control>
    <control controlID="425E3EB4-EF3E-485C-B6D4-A2D806508882" controlTypeID="Label" isShow="True" caption="%E5%8D%95%E8%A1%8C%E6%96%87%E5%AD%97" x="40" y="115" w="36" h="24" measuredW="0" measuredH="0" zOrder="8" locked="False" sizeLocked="False">
      <controlProperties>
        <basic color="0" borderVisible="True" borderColor="4284900966" isAutoSize="True" status="MsEnabled" opacity="1" isCommentCom="False" canMove="True" alias="" rotation="0"/>
        <states/>
        <verticalScrollbarShow>False</verticalScrollbarShow>
        <verticalScrollbarProgress>0</verticalScrollbarProgress>
        <horizontalScrollbarShow>False</horizontalScrollbarShow>
        <horizontalScrollbarProgress>0</horizontalScrollbarProgress>
        <links eventType="AtClick" animate="AmNone" animateAutoDelay="0" animateDuration="500">
          <link targetPageID="" linkType="ltPageLink" isApplyIncludePage="False" title="%E9%93%BE%E6%8E%A5">
            <area shape="0" alt="" ID="{B5DD3AEC-4156-4457-B986-F4619B580549}" coords="(0,0,36,24)"/>
          </link>
        </links>
        <interactiveData>
          <entry title="">
            <area shape="0" alt="" ID="{279A08D6-AE05-49EF-BB83-85397CDB9418}" coords="(0,0,36,24)"/>
            <events title=""/>
          </entry>
        </interactiveData>
        <textSet textColor="4278190080" textSize="18" lineSpacingMultiple="1" textAlign="HaLeft" textVAlign="VaTop" textWordWrap="True" lineSpacing="24" textStyles="[]" useDefaultTextSize="False">
          <font family="%E5%BE%AE%E8%BD%AF%E9%9B%85%E9%BB%91" displayName="%E5%BE%AE%E8%BD%AF%E9%9B%85%E9%BB%91" postScript="" weightStyle="Regular" weight="400" isBold="False" isItalic="False"/>
          <text>%E4%B8%BB%E9%A2%98</text>
        </textSet>
        <selectedIndex>-1</selectedIndex>
        <selectedColor>4282501083</selectedColor>
        <textPadding>0</textPadding>
      </controlProperties>
    </control>
    <control controlID="0434DACD-0429-4540-A8C1-C070F2B0A068" controlTypeID="TextInput" isShow="True" caption="%E8%BE%93%E5%85%A5%E6%A1%86" x="135" y="118" w="196" h="19" measuredW="138" measuredH="36" zOrder="9" locked="False" sizeLocked="False">
      <controlProperties>
        <basic color="4294967295" borderVisible="True" borderColor="4284900966" isAutoSize="False" status="MsEnabled" opacity="1" isCommentCom="False" canMove="True" alias="" rotation="0"/>
        <states/>
        <verticalScrollbarShow>False</verticalScrollbarShow>
        <verticalScrollbarProgress>0</verticalScrollbarProgress>
        <horizontalScrollbarShow>False</horizontalScrollbarShow>
        <horizontalScrollbarProgress>0</horizontalScrollbarProgress>
        <links eventType="AtClick" animate="AmNone" animateAutoDelay="0" animateDuration="500">
          <link targetPageID="" linkType="ltPageLink" isApplyIncludePage="False" title="%E9%93%BE%E6%8E%A5">
            <area shape="0" alt="" ID="{02DCF73A-F9FC-47C5-AE4D-02ECCA6EBC80}" coords="(0,0,196,19)"/>
          </link>
        </links>
        <interactiveData>
          <entry title="">
            <area shape="0" alt="" ID="{9C7F8284-8C55-4187-885D-C6186FCC7CD3}" coords="(0,0,196,19)"/>
            <events title=""/>
          </entry>
        </interactiveData>
        <textSet textColor="4278190080" textSize="14" lineSpacingMultiple="1" textAlign="HaLeft" textVAlign="VaMiddle" textWordWrap="True" lineSpacing="18" textStyles="[]" useDefaultTextSize="True">
          <font family="%E5%BE%AE%E8%BD%AF%E9%9B%85%E9%BB%91" displayName="%E5%BE%AE%E8%BD%AF%E9%9B%85%E9%BB%91" postScript="" weightStyle="Regular" weight="400" isBold="False" isItalic="False"/>
          <text>%E8%AF%B7%E5%A1%AB%E5%86%99%E4%B8%BB%E9%A2%98</text>
        </textSet>
        <selectedIndex>-1</selectedIndex>
        <selectedColor>4282501083</selectedColor>
        <textPadding>0</textPadding>
        <canInput>True</canInput>
      </controlProperties>
    </control>
    <control controlID="D5F10813-E87B-44D5-9A0F-DC8A9D1445EF" controlTypeID="HotSpot" isShow="True" caption="%E7%83%AD%E5%8C%BA" x="14" y="10" w="60" h="60" measuredW="48" measuredH="48" zOrder="10" locked="False" sizeLocked="False">
      <controlProperties>
        <basic color="4294967295" borderVisible="True" borderColor="4284900966" isAutoSize="False" status="MsEnabled" opacity="1" isCommentCom="False" canMove="True" alias="" rotation="0"/>
        <states/>
        <verticalScrollbarShow>False</verticalScrollbarShow>
        <verticalScrollbarProgress>0</verticalScrollbarProgress>
        <horizontalScrollbarShow>False</horizontalScrollbarShow>
        <horizontalScrollbarProgress>0</horizontalScrollbarProgress>
        <links eventType="AtClick" animate="AmNone" animateAutoDelay="0" animateDuration="500">
          <link targetPageID="06D7EFAE-9A9A-4861-B22D-7DB0853888F5" linkType="ltPageLink" isApplyIncludePage="False" title="%E9%A6%96%E9%A1%B5">
            <area shape="0" alt="" ID="{72292F07-8BDA-4361-A741-09BAD72C201F}" coords="(0,0,60,60)"/>
          </link>
        </links>
        <interactiveData>
          <entry title="">
            <area shape="0" alt="" ID="{38C662B5-8EE3-4D6B-863C-4A5B9FA025D5}" coords="(0,0,60,60)"/>
            <events title=""/>
          </entry>
        </interactiveData>
      </controlProperties>
    </control>
    <control controlID="57EC606D-6BE8-4ED4-AEFA-A4883141D742" controlTypeID="Button" isShow="True" caption="%E6%8C%89%E9%92%AE" x="137" y="538" w="120" h="48" measuredW="78" measuredH="36" zOrder="11" locked="False" sizeLocked="False">
      <controlProperties>
        <basic color="4294967295" borderVisible="True" borderColor="4284900966" isAutoSize="False" status="MsEnabled" opacity="1" isCommentCom="False" canMove="True" alias="" rotation="0"/>
        <states/>
        <verticalScrollbarShow>False</verticalScrollbarShow>
        <verticalScrollbarProgress>0</verticalScrollbarProgress>
        <horizontalScrollbarShow>False</horizontalScrollbarShow>
        <horizontalScrollbarProgress>0</horizontalScrollbarProgress>
        <links eventType="AtClick" animate="AmNone" animateAutoDelay="0" animateDuration="500">
          <link targetPageID="" linkType="ltPageLink" isApplyIncludePage="False" title="%E9%93%BE%E6%8E%A5">
            <area shape="0" alt="" ID="{4194E906-E076-4602-97CB-E56C8F67884C}" coords="(0,0,120,48)"/>
          </link>
        </links>
        <interactiveData>
          <entry title="">
            <area shape="0" alt="" ID="{EE0571F5-14C4-4510-831C-D259594BA19D}" coords="(0,0,120,48)"/>
            <events title="">
              <event eventType="atClick" isChecked="True">
                <behaviour title="" isChecked="True" isWait="False" isLoop="False" execMode="emParallel">
                  <target targetID="9B2D7910-2477-4571-84CD-9CBE6FD80466" isChecked="True" isAutoRecovery="False" isLoop="False" execMode="emSequence">
                    <command name="Popup State Change" isChecked="True" descrition="">
                      <param name="AniInterpolation" value="0" varType="3" description=""/>
                      <param name="AniDuration" value="200" varType="3" description=""/>
                      <param name="AniAutoReverse" value="False" varType="11" description=""/>
                      <param name="AniLoop" value="False" varType="11" description=""/>
                      <param name="AniInterpolationTypeOut" value="False" varType="11" description=""/>
                      <param name="Delay" value="0" varType="3" description=""/>
                      <param name="Value" value="2" varType="3" description=""/>
                      <param name="AniType" value="0" varType="3" description=""/>
                    </command>
                  </target>
                </behaviour>
              </event>
            </events>
          </entry>
        </interactiveData>
        <textSet textColor="4278190080" textSize="14" lineSpacingMultiple="1" textAlign="HaCenter" textVAlign="VaMiddle" textWordWrap="True" lineSpacing="18" textStyles="[]" useDefaultTextSize="True">
          <font family="%E5%BE%AE%E8%BD%AF%E9%9B%85%E9%BB%91" displayName="%E5%BE%AE%E8%BD%AF%E9%9B%85%E9%BB%91" postScript="" weightStyle="Regular" weight="400" isBold="False" isItalic="False"/>
          <text>%E7%A1%AE%E5%AE%9A</text>
        </textSet>
        <selectedIndex>-1</selectedIndex>
        <selectedColor>4282501083</selectedColor>
        <textPadding>0</textPadding>
        <radius>4</radius>
        <radiusIsPercent>False</radiusIsPercent>
        <buttonStatus>BsNormal</buttonStatus>
        <thickness>1</thickness>
        <isAutoTextColor>False</isAutoTextColor>
        <borderColor>4284900966</borderColor>
      </controlProperties>
    </control>
    <control controlID="392421F1-8C47-4AA5-8583-AC0127C2F433" controlTypeID="TextInput" isShow="True" caption="%E8%BE%93%E5%85%A5%E6%A1%86" x="137" y="479" w="138" h="39" measuredW="138" measuredH="36" zOrder="12" locked="False" sizeLocked="False">
      <controlProperties>
        <basic color="4294967295" borderVisible="True" borderColor="4284900966" isAutoSize="False" status="MsEnabled" opacity="1" isCommentCom="False" canMove="True" alias="" rotation="0"/>
        <states/>
        <verticalScrollbarShow>False</verticalScrollbarShow>
        <verticalScrollbarProgress>0</verticalScrollbarProgress>
        <horizontalScrollbarShow>False</horizontalScrollbarShow>
        <horizontalScrollbarProgress>0</horizontalScrollbarProgress>
        <links eventType="AtClick" animate="AmNone" animateAutoDelay="0" animateDuration="500">
          <link targetPageID="" linkType="ltPageLink" isApplyIncludePage="False" title="%E9%93%BE%E6%8E%A5">
            <area shape="0" alt="" ID="{88CB11BA-9A06-4C08-A6DC-69FA73F3467B}" coords="(0,0,138,39)"/>
          </link>
        </links>
        <interactiveData>
          <entry title="">
            <area shape="0" alt="" ID="{33558A7A-0B65-47B7-B767-4D4C3BC57841}" coords="(0,0,138,39)"/>
            <events title=""/>
          </entry>
        </interactiveData>
        <textSet textColor="4278190080" textSize="14" lineSpacingMultiple="1" textAlign="HaLeft" textVAlign="VaMiddle" textWordWrap="True" lineSpacing="18" textStyles="[]" useDefaultTextSize="True">
          <font family="%E5%BE%AE%E8%BD%AF%E9%9B%85%E9%BB%91" displayName="%E5%BE%AE%E8%BD%AF%E9%9B%85%E9%BB%91" postScript="" weightStyle="Regular" weight="400" isBold="False" isItalic="False"/>
          <text>%E8%AF%B7%E8%BE%93%E5%85%A5%E9%AA%8C%E8%AF%81%E7%A0%81</text>
        </textSet>
        <selectedIndex>-1</selectedIndex>
        <selectedColor>4282501083</selectedColor>
        <textPadding>0</textPadding>
        <canInput>True</canInput>
      </controlProperties>
    </control>
    <control controlID="EA43D9CB-BCA9-4B04-B980-5277C552C789" controlTypeID="Label" isShow="True" caption="%E5%8D%95%E8%A1%8C%E6%96%87%E5%AD%97" x="40" y="493" w="41" h="19" measuredW="0" measuredH="0" zOrder="13" locked="False" sizeLocked="False">
      <controlProperties>
        <basic color="0" borderVisible="True" borderColor="4284900966" isAutoSize="True" status="MsEnabled" opacity="1" isCommentCom="False" canMove="True" alias="" rotation="0"/>
        <states/>
        <verticalScrollbarShow>False</verticalScrollbarShow>
        <verticalScrollbarProgress>0</verticalScrollbarProgress>
        <horizontalScrollbarShow>False</horizontalScrollbarShow>
        <horizontalScrollbarProgress>0</horizontalScrollbarProgress>
        <links eventType="AtClick" animate="AmNone" animateAutoDelay="0" animateDuration="500">
          <link targetPageID="" linkType="ltPageLink" isApplyIncludePage="False" title="%E9%93%BE%E6%8E%A5">
            <area shape="0" alt="" ID="{34B5CE97-E46F-4531-8AC1-89B6FEEAE8A3}" coords="(0,0,41,19)"/>
          </link>
        </links>
        <interactiveData>
          <entry title="">
            <area shape="0" alt="" ID="{4BFA3A78-755A-4625-ABF8-79844FAE3A85}" coords="(0,0,41,19)"/>
            <events title=""/>
          </entry>
        </interactiveData>
        <textSet textColor="4278190080" textSize="14" lineSpacingMultiple="1" textAlign="HaLeft" textVAlign="VaTop" textWordWrap="True" lineSpacing="18" textStyles="[]" useDefaultTextSize="True">
          <font family="%E5%BE%AE%E8%BD%AF%E9%9B%85%E9%BB%91" displayName="%E5%BE%AE%E8%BD%AF%E9%9B%85%E9%BB%91" postScript="" weightStyle="Regular" weight="400" isBold="False" isItalic="False"/>
          <text>%E9%AA%8C%E8%AF%81%E7%A0%81</text>
        </textSet>
        <selectedIndex>-1</selectedIndex>
        <selectedColor>4282501083</selectedColor>
        <textPadding>0</textPadding>
      </controlProperties>
    </control>
    <control controlID="74C9731D-6026-4A9B-90A7-3C5CEF507A4B" controlTypeID="Button" isShow="True" caption="%E6%8C%89%E9%92%AE" x="285" y="420" w="78" h="37" measuredW="78" measuredH="36" zOrder="14" locked="False" sizeLocked="False">
      <controlProperties>
        <basic color="4294967295" borderVisible="True" borderColor="4284900966" isAutoSize="False" status="MsEnabled" opacity="1" isCommentCom="False" canMove="True" alias="" rotation="0"/>
        <states/>
        <verticalScrollbarShow>False</verticalScrollbarShow>
        <verticalScrollbarProgress>0</verticalScrollbarProgress>
        <horizontalScrollbarShow>False</horizontalScrollbarShow>
        <horizontalScrollbarProgress>0</horizontalScrollbarProgress>
        <links eventType="AtClick" animate="AmNone" animateAutoDelay="0" animateDuration="500">
          <link targetPageID="" linkType="ltPageLink" isApplyIncludePage="False" title="%E9%93%BE%E6%8E%A5">
            <area shape="0" alt="" ID="{D12B7FA9-AFE9-480D-ADC3-1A0B47787F27}" coords="(0,0,78,37)"/>
          </link>
        </links>
        <interactiveData>
          <entry title="">
            <area shape="0" alt="" ID="{D88E2B1B-2D06-49A6-8A02-B4A704975F5D}" coords="(0,0,78,37)"/>
            <events title=""/>
          </entry>
        </interactiveData>
        <textSet textColor="4278190080" textSize="14" lineSpacingMultiple="1" textAlign="HaCenter" textVAlign="VaMiddle" textWordWrap="True" lineSpacing="18" textStyles="[]" useDefaultTextSize="True">
          <font family="%E5%BE%AE%E8%BD%AF%E9%9B%85%E9%BB%91" displayName="%E5%BE%AE%E8%BD%AF%E9%9B%85%E9%BB%91" postScript="" weightStyle="Regular" weight="400" isBold="False" isItalic="False"/>
          <text>%E5%8F%91%E9%80%81%E9%AA%8C%E8%AF%81%E7%A0%81</text>
        </textSet>
        <selectedIndex>-1</selectedIndex>
        <selectedColor>4282501083</selectedColor>
        <textPadding>0</textPadding>
        <radius>4</radius>
        <radiusIsPercent>False</radiusIsPercent>
        <buttonStatus>BsNormal</buttonStatus>
        <thickness>1</thickness>
        <isAutoTextColor>False</isAutoTextColor>
        <borderColor>4284900966</borderColor>
      </controlProperties>
    </control>
    <control controlID="9B2D7910-2477-4571-84CD-9CBE6FD80466" controlTypeID="AlertWindow" isShow="True" caption="%E5%BC%B9%E7%AA%97" x="178" y="466" w="46" h="46" measuredW="0" measuredH="0" zOrder="15" locked="False" sizeLocked="False">
      <controlProperties isBackgroundFade="True" aniType_Mobile="aniFade" aniType="dnNone" closeByClickMode="cmClickOutSizeArea" closeByKeyModes="[kmEsc,kmEnter]" isShowBackground="True" delayBeforePopup="0" aniDuration="200" positionPolicy="ppFree" positionMargin="0" positionScreenMode="psCenter" positionComMode="pcBottom">
        <basic color="1879048192" borderVisible="False" borderColor="4284900966" isAutoSize="False" status="MsEnabled" opacity="1" isCommentCom="False" canMove="True" alias="" rotation="0"/>
        <states/>
        <verticalScrollbarShow>False</verticalScrollbarShow>
        <verticalScrollbarProgress>0</verticalScrollbarProgress>
        <horizontalScrollbarShow>False</horizontalScrollbarShow>
        <horizontalScrollbarProgress>0</horizontalScrollbarProgress>
        <links eventType="AtClick" animate="AmNone" animateAutoDelay="0" animateDuration="500">
          <link targetPageID="" linkType="ltPageLink" isApplyIncludePage="False" title="%E9%93%BE%E6%8E%A5">
            <area shape="0" alt="" ID="{02F7A749-5B97-44E4-97F2-E4C9F8240171}" coords="(0,0,46,46)"/>
          </link>
        </links>
        <interactiveData>
          <entry title="">
            <area shape="0" alt="" ID="{30EE5277-3C0F-48C5-8F72-18756A0D934C}" coords="(0,0,46,46)"/>
            <events title=""/>
          </entry>
        </interactiveData>
        <groupChildrenDescriptors>
          <control controlID="3D3F337D-5FB7-4774-BE10-3AAEA4316862" controlTypeID="Panel" isShow="True" caption="%E9%9D%A2%E6%9D%BF" x="0" y="0" w="375" h="667" measuredW="0" measuredH="0" zOrder="0" locked="True" sizeLocked="False">
            <controlProperties>
              <basic color="1879048192" borderVisible="False" borderColor="4284900966" isAutoSize="False" status="MsEnabled" opacity="1" isCommentCom="False" canMove="False" alias="background" rotation="0"/>
              <states/>
              <verticalScrollbarShow>False</verticalScrollbarShow>
              <verticalScrollbarProgress>0</verticalScrollbarProgress>
              <horizontalScrollbarShow>False</horizontalScrollbarShow>
              <horizontalScrollbarProgress>0</horizontalScrollbarProgress>
              <links eventType="AtClick" animate="AmNone" animateAutoDelay="0" animateDuration="500">
                <link targetPageID="" linkType="ltPageLink" isApplyIncludePage="False" title="%E9%93%BE%E6%8E%A5">
                  <area shape="0" alt="" ID="{C6D178AA-99F0-4FE1-B00D-43B5F5C3A057}" coords="(0,0,375,667)"/>
                </link>
              </links>
              <interactiveData>
                <entry title="">
                  <area shape="0" alt="" ID="{F670F429-88F6-44AB-AE38-A1C660D4538F}" coords="(0,0,375,667)"/>
                  <events title=""/>
                </entry>
              </interactiveData>
              <groupChildrenDescriptors>
                <control controlID="C7E00703-5869-402F-9D9C-2B5C9F531928" controlTypeID="Border" isShow="True" caption="Border" x="0" y="0" w="375" h="667" measuredW="0" measuredH="0" zOrder="0" locked="True" sizeLocked="False">
                  <controlProperties>
                    <basic color="4294967295" borderVisible="False" borderColor="4284900966" isAutoSize="False" status="MsEnabled" opacity="1" isCommentCom="False" canMove="True" alias="borderLayer" rotation="0"/>
                    <states/>
                    <verticalScrollbarShow>False</verticalScrollbarShow>
                    <verticalScrollbarProgress>0</verticalScrollbarProgress>
                    <horizontalScrollbarShow>False</horizontalScrollbarShow>
                    <horizontalScrollbarProgress>0</horizontalScrollbarProgress>
                    <links eventType="AtClick" animate="AmNone" animateAutoDelay="0" animateDuration="500">
                      <link targetPageID="" linkType="ltPageLink" isApplyIncludePage="False" title="%E9%93%BE%E6%8E%A5">
                        <area shape="0" alt="" ID="{AFAACE27-AF31-4071-A1BC-396220886D1B}" coords="(0,0,375,667)"/>
                      </link>
                    </links>
                    <interactiveData>
                      <entry title="">
                        <area shape="0" alt="" ID="{2DF90609-A982-4CF8-9317-1F9F0C83502C}" coords="(0,0,375,667)"/>
                        <events title=""/>
                      </entry>
                    </interactiveData>
                    <thickness>1</thickness>
                    <dashMode>SdSolid</dashMode>
                  </controlProperties>
                </control>
              </groupChildrenDescriptors>
              <thinkness>1</thinkness>
              <dashMode>SdSolid</dashMode>
            </controlProperties>
          </control>
          <control controlID="2683F0A6-6072-4060-8550-65F5B7807A23" controlTypeID="Alert" isShow="True" caption="%E6%8F%90%E7%A4%BA%E6%A1%86" x="62" y="252" w="293" h="213" measuredW="200" measuredH="130" zOrder="1" locked="False" sizeLocked="False">
            <controlProperties>
              <basic color="4294967295" borderVisible="True" borderColor="4284900966" isAutoSize="False" status="MsEnabled" opacity="1" isCommentCom="False" canMove="True" alias="content" rotation="0"/>
              <states/>
              <verticalScrollbarShow>False</verticalScrollbarShow>
              <verticalScrollbarProgress>0</verticalScrollbarProgress>
              <horizontalScrollbarShow>False</horizontalScrollbarShow>
              <horizontalScrollbarProgress>0</horizontalScrollbarProgress>
              <links eventType="AtClick" animate="AmNone" animateAutoDelay="0" animateDuration="500">
                <link targetPageID="78DA46E7-654B-4505-AA38-571E3B57B473" linkType="ltPageLink" isApplyIncludePage="False" title="%E8%BF%94%E5%9B%9E">
                  <area shape="0" alt="" ID="{B1BF1260-BF52-4381-A57A-DB34887F648E}" coords="(5,178,288,208)"/>
                </link>
                <link targetPageID="" linkType="ltPageLink" isApplyIncludePage="False" title="">
                  <area shape="0" alt="" ID="{6C7A2B88-C198-41D2-9362-BBA3E4514F4D}" coords="(0,0,0,0)"/>
                </link>
              </links>
              <interactiveData>
                <entry title="%E8%BF%94%E5%9B%9E">
                  <area shape="0" alt="" ID="{DEBB9F7F-E93B-4AEF-AB45-01538FE1C17B}" coords="(5,178,288,208)"/>
                  <events title=""/>
                </entry>
                <entry title="">
                  <area shape="0" alt="" ID="{28750E4D-2E81-4E25-AA4A-1E54037B2F4E}" coords="(0,0,0,0)"/>
                  <events title=""/>
                </entry>
              </interactiveData>
              <textSet textColor="4278190080" textSize="14" lineSpacingMultiple="1" textAlign="HaCenter" textVAlign="VaTop" textWordWrap="True" lineSpacing="18" textStyles="[]" useDefaultTextSize="True">
                <font family="%E5%BE%AE%E8%BD%AF%E9%9B%85%E9%BB%91" displayName="%E5%BE%AE%E8%BD%AF%E9%9B%85%E9%BB%91" postScript="" weightStyle="Regular" weight="400" isBold="False" isItalic="False"/>
                <text>%E6%8F%90%E7%A4%BA%0D%0A%E6%82%A8%E7%9A%84%E6%8A%95%E8%AF%89%E7%BC%96%E5%8F%B7%E6%98%AF%EF%BC%9A9900%0D%0A%E8%AF%B7%E6%82%A8%E8%AE%B0%E4%BD%8F%E6%8A%95%E8%AF%89%E7%BC%96%E5%8F%B7%0D%0A%E4%BB%A5%E6%96%B9%E4%BE%BF%E7%BD%91%E4%B8%8A%E6%8A%95%E8%AF%89%E7%8A%B6%E6%80%81%E6%9F%A5%E8%AF%A2%EF%BC%81%0D%0A%0D%0A%E8%BF%94%E5%9B%9E</text>
              </textSet>
              <selectedIndex>0</selectedIndex>
              <selectedColor>4282501083</selectedColor>
              <textPadding>0</textPadding>
              <selection>MBNone</selection>
            </controlProperties>
          </control>
        </groupChildrenDescriptors>
      </controlProperties>
    </control>
  </controls>
  <param>
    <backgroundColor>4294967295</backgroundColor>
    <fontSize>0</fontSize>
    <fontFamily/>
    <guideLines/>
  </param>
</mockup>